{
    "@class": "com.kony.gen.viz.model.container.KVizScrollFlexForm",
    "DNDConfig": null,
    "_margin_": [
        0,
        0,
        0,
        0
    ],
    "_orientation_": 1,
    "_padding_": [
        0,
        0,
        0,
        0
    ],
    "_percent_": true,
    "_skin_": "s31eff9535d64f50af633b7378188c92",
    "_title_": null,
    "addWidgetsdone": false,
    "allboxes": [],
    "canUpdateUI": true,
    "children": [
        "Flex0b4408de1aa6840"
    ],
    "containerId": true,
    "containerweight": 100,
    "currentLocale": "default",
    "device": "GalaxyS5",
    "displayorientation": 3,
    "enabledforidletimeout": false,
    "id": "tempRegHead",
    "info": null,
    "initdone": false,
    "inputaccessoryviewtype": 4,
    "intransitionconfig": {
        "formTransition": "None"
    },
    "iscustomlayout": false,
    "isvisible": true,
    "kuid": "a8c3d144f3e9454cbc619e189c1b6be5",
    "name": "kony.ui.Form2",
    "needappmenu": true,
    "outtransitionconfig": {
        "formTransition": "None"
    },
    "paddinginpixel": false,
    "platform": "android",
    "prevDevice": "iPhoneXS",
    "prevPlatform": "iphone",
    "retaincontentalignment": false,
    "retainflexpositionproperties": false,
    "retainscrollposition": false,
    "shellCSS": "and_GalaxyS5",
    "titlebar": true,
    "type": 3,
    "wType": "Form"
}