{
    "DNDConfig": null,
    "__parentReadjusting__": false,
    "_height_": {
        "type": "ref",
        "value": "preferred"
    },
    "_left_": {
        "type": "string",
        "value": "1%"
    },
    "_margin_": [
        0,
        0,
        0,
        0
    ],
    "_orientation_": 6,
    "_padding_": [
        0,
        0,
        0,
        0
    ],
    "_percent_": true,
    "_skin_": "s7d12891eecb43a99e49be26d055517f",
    "_top_": {
        "type": "string",
        "value": "5dp"
    },
    "_width_": {
        "type": "string",
        "value": "98%"
    },
    "allboxes": [],
    "autogrowmode": 1,
    "canUpdateUI": true,
    "children": [
        "CopylblCustName0j8a5ff5fd9264d",
        "CopylblMilkBNV0fd7df826751140"
    ],
    "clipbounds": true,
    "containerweight": 100,
    "enablescrolling": true,
    "id": "CopyflxCustName0gd34f0aa006544",
    "info": null,
    "iscustomlayout": false,
    "isvisible": true,
    "kuid": "b7c3f8e93fe449b4ae5d2607369214e9",
    "layouttype": 2,
    "name": "kony.ui.FlexContainer",
    "parent": "CopyflxCustDetails0e71d0d6c5d4a4d",
    "pf": "frmInvoice",
    "retaincontentalignment": false,
    "retainflexpositionproperties": false,
    "retainflowhorizontalalignment": false,
    "snapgridsize": 10,
    "snaptogrid": true,
    "wType": "FlexContainer",
    "widgetalignment": 1,
    "zindex": 1
}