{
    "DNDConfig": null,
    "__parentReadjusting__": false,
    "_height_": {
        "type": "ref",
        "value": "preferred"
    },
    "_left_": {
        "type": "string",
        "value": "4%"
    },
    "_margin_": [
        0,
        0,
        0,
        0
    ],
    "_orientation_": 6,
    "_padding_": [
        0,
        0,
        0,
        0
    ],
    "_percent_": true,
    "_skin_": "s7d12891eecb43a99e49be26d055517f",
    "_top_": {
        "type": "string",
        "value": "3%"
    },
    "_width_": {
        "type": "string",
        "value": "92%"
    },
    "allboxes": [],
    "autogrowmode": 1,
    "canUpdateUI": true,
    "children": [
        "flxBillingp",
        "flxCustName",
        "CopyflxCustName0f13954362a384a",
        "CopyflxCustName0fe15ed9f355c41",
        "flxdummy"
    ],
    "clipbounds": true,
    "containerweight": 100,
    "enablescrolling": true,
    "id": "flxCustDetails",
    "info": null,
    "iscustomlayout": false,
    "isvisible": true,
    "kuid": "i0f3aea4e0004ba1b101750ea66d7520",
    "layouttype": 4,
    "name": "kony.ui.FlexContainer",
    "parent": "FlexScrollContainer0e322fb4c50a847",
    "pf": "frmInvoice",
    "retaincontentalignment": false,
    "retainflexpositionproperties": false,
    "retainflowhorizontalalignment": false,
    "snapgridsize": 10,
    "snaptogrid": true,
    "wType": "FlexContainer",
    "widgetalignment": 1,
    "zindex": 1
}